uniscan/__init__.py
uniscan-0.2.0.dist-info/licenses/LICENSE
uniscan-0.2.0.dist-info/METADATA
uniscan-0.2.0.dist-info/WHEEL
uniscan-0.2.0.dist-info/entry_points.txt
uniscan-0.2.0.dist-info/top_level.txt
uniscan-0.2.0.dist-info/RECORD
