Metadata-Version: 2.4
Name: uniscan
Version: 0.2.0
Summary: Redirect package for the renamed Usentinel project.
Author: Tianjiao Li
License: MIT License
Project-URL: Homepage, https://github.com/TLI-1994/Usentinel
Project-URL: Repository, https://github.com/TLI-1994/Usentinel
Project-URL: Issues, https://github.com/TLI-1994/Usentinel/issues
Classifier: Development Status :: 7 - Inactive
Classifier: License :: OSI Approved :: MIT License
Classifier: Programming Language :: Python :: 3
Requires-Python: >=3.8
License-File: LICENSE
Requires-Dist: usentinel>=0.2.0
Dynamic: license-file
